# This file is optional and here as an example of how to activate the build runner
# FEEL FREE TO DELETE!!

# If playing as a different race, make a file similar to this but change filename:
# `zerg_builds.yml` or `terran_builds.yml`


# Save the game opening and result to disk?
# Setting to `True` allows Ares to select a new opening after defeat
UseData: True
# How should we choose a build? Cycle is the only option for now
BuildSelection: Cycle
# For each Race / Opponent ID choose a build selection
BuildChoices:
    # test_123 is active if Debug: True (set via a `config.yml` file)
    test_123:
        BotName: Test
        Cycle:
            - OneOneOne

    Protoss:
        BotName: ProtossRace
        Cycle:
            - OneOneOne

    Random:
        BotName: RandomRace
        Cycle:
            - OneOneOne

    Terran:
        BotName: TerranRace
        Cycle:
            - OneOneOne

    Zerg:
        BotName: ZergRace
        Cycle:
            - OneOneOne

Builds:
    OneOneOne:
        ConstantWorkerProductionTill: 42
        # TODO: Tidy this up so only the initial build is completed
        #   Currently used as a hacky way to get structures down, and not dynamic at all
        #   After https://github.com/AresSC2/phobos/issues/1 is completed
        OpeningBuildOrder:
            - 14 supply @ ramp
            - 15 expand
            - 18 expand
            - 15 gas
            - 16 barracks @ ramp
            - 19 orbital
            - 19 reaper
            - 19 expand
            - 19 supply @ ramp
            - 20 factory
            - 21 marine
            - 22 gas
            - 23 barracksreactor
            - 24 starport
            - 25 widowmine
            - 25 orbital
            - 26 supply
            - 27 widowmine
            - 29 medivac
            - 29 factorytechlab
            - 29 gas
            - 29 supply
            - 29 barracks
            - 29 barracks
            - 29 starporttechlab
            - 29 supply
            - 29 raven
            - 29 siegetank
            - 29 supply
            - 29 supply
            - 42 supply
            - 42 supply
            - 42 barrackstechlab
            - 42 supply
            - 52 barracks
            - 52 supply
            - 52 supply
            - 60 barracks
            - 60 supply
            - 64 supply
            - 66 barracks
            - 70 supply
            - 78 supply
            - 85 supply
            - 90 supply
            - 96 supply
            - 96 barracks
            - 102 supply
            - 110 supply
            - 120 supply
            - 130 supply
            - 138 supply
            - 138 barracks

